{
  "$schema": "https://developer.microsoft.com/json-schemas/fabric/item/report/definition/visualContainer/2.6.0/schema.json",
  "name": "dea7510770bcdab36741",
  "position": {
    "x": 714.71777576870386,
    "y": 1341.1572266684639,
    "z": 19000,
    "height": 115,
    "width": 215,
    "tabOrder": 44000
  },
  "visual": {
    "visualType": "card",
    "query": {
      "queryState": {
        "Values": {
          "projections": [
            {
              "field": {
                "Measure": {
                  "Expression": {
                    "SourceRef": {
                      "Entity": "dim_group"
                    }
                  },
                  "Property": "socialsignupsP5W"
                }
              },
              "queryRef": "dim_group.socialsignupsP5W",
              "nativeQueryRef": "New Sign Ups",
              "displayName": "New Sign Ups"
            }
          ]
        }
      },
      "sortDefinition": {
        "sort": [
          {
            "field": {
              "Measure": {
                "Expression": {
                  "SourceRef": {
                    "Entity": "dim_group"
                  }
                },
                "Property": "socialsignupsP5W"
              }
            },
            "direction": "Descending"
          }
        ],
        "isDefaultSort": true
      }
    },
    "drillFilterOtherVisuals": true
  }
}